bifrost_dashboard/__init__.py
bifrost_dashboard/reporter.py
bifrost_dashboard/reporter_admin.py
bifrost_dashboard/run_checker.py
bifrost_dashboard/components/__init__.py
bifrost_dashboard/components/admin.py
bifrost_dashboard/components/aggregate_report.py
bifrost_dashboard/components/filter.py
bifrost_dashboard/components/global_vars.py
bifrost_dashboard/components/images.py
bifrost_dashboard/components/import_data.py
bifrost_dashboard/components/link_to_files.py
bifrost_dashboard/components/resequence_report.py
bifrost_dashboard/components/sample_report.py
bifrost_dashboard/components/table.py
bifrost_dashboard/components/virtual_runs.py
bifrost_dashboard/data/assets/10_jquery-3.3.1.min.js
bifrost_dashboard/data/assets/10_sb-admin-2.min.css
bifrost_dashboard/data/assets/20_custom.css
bifrost_dashboard/data/assets/20_sb-admin-2.min.js
bifrost_dashboard/data/assets/30_dash_callbacks.js
bifrost_dashboard/data/assets/img/008-bacteria-2.svg
bifrost_dashboard/data/assets/img/009-bacteria-1.svg
bifrost_dashboard/data/assets/img/010-bacteria.svg
bifrost_dashboard/data/assets/img/bifrost-logo-white@2x.png
bifrost_dashboard/data/assets/img/default.svg
bifrost_dashboard/data/assets/img/enterobacter.svg
bifrost_dashboard/data/assets/img/enterococcus.svg
bifrost_dashboard/data/assets/img/escherichia.svg
bifrost_dashboard/data/assets/img/legionella.svg
bifrost_dashboard/data/assets/img/pseudomonas.svg
bifrost_dashboard/data/assets/img/report.png
bifrost_dashboard/data/assets/img/salmonella.svg
bifrost_dashboard/data/assets/img/staphylococcus.svg
bifrost_dashboard-0.0.6.data/scripts/bifrost_dashboard_start
bifrost_dashboard-0.0.6.dist-info/METADATA
bifrost_dashboard-0.0.6.dist-info/WHEEL
bifrost_dashboard-0.0.6.dist-info/entry_points.txt
bifrost_dashboard-0.0.6.dist-info/top_level.txt
bifrost_dashboard-0.0.6.dist-info/RECORD
